INSTALL.rst
LICENSE
MANIFEST.in
NEWS.rst
README.rst
pyproject.toml
requirements.txt
setup.py
bin/AlignSets.py
bin/AssemblePairs.py
bin/BuildConsensus.py
bin/ClusterSets.py
bin/CollapseSeq.py
bin/ConvertHeaders.py
bin/EstimateError.py
bin/FilterSeq.py
bin/MaskPrimers.py
bin/PairSeq.py
bin/ParseHeaders.py
bin/ParseLog.py
bin/SplitSeq.py
bin/UnifyHeaders.py
presto/Annotation.py
presto/Applications.py
presto/Commandline.py
presto/Defaults.py
presto/IO.py
presto/Multiprocessing.py
presto/Sequence.py
presto/Version.py
presto/__init__.py
presto.egg-info/PKG-INFO
presto.egg-info/SOURCES.txt
presto.egg-info/dependency_links.txt
presto.egg-info/not-zip-safe
presto.egg-info/requires.txt
presto.egg-info/top_level.txt
tests/test_Annotation.py
tests/test_AssemblePairs.py
tests/test_BuildConsensus.py
tests/test_ClusterSets.py
tests/test_CollapseSeq.py
tests/test_ConvertHeaders.py
tests/test_EstimateError.py
tests/test_IO.py
tests/test_MaskPrimers.py
tests/test_Sequence.py
tests/test_UnifyHeaders.py