Metadata-Version: 2.4
Name: presto
Version: 0.7.6
Summary: A bioinformatics toolkit for processing high-throughput lymphocyte receptor sequencing data.
Home-page: http://presto.readthedocs.io
Download-URL: https://github.com/immcantation/presto/tags
Author: Jason Anthony Vander Heiden
Author-email: immcantation@googlegroups.com
License: GNU Affero General Public License 3 (AGPL-3)
Keywords: bioinformatics,sequencing,immunology,adaptive immunity,immunoglobulin,AIRR-seq,Rep-Seq,B cell repertoire analysis,adaptive immune receptor repertoires
Classifier: Development Status :: 4 - Beta
Classifier: Environment :: Console
Classifier: Intended Audience :: Science/Research
Classifier: Natural Language :: English
Classifier: Operating System :: OS Independent
Classifier: Programming Language :: Python :: 3.7
Classifier: Topic :: Scientific/Engineering :: Bio-Informatics
License-File: LICENSE
Requires-Dist: numpy>=1.8
Requires-Dist: scipy>=0.14
Requires-Dist: pandas>=0.24
Requires-Dist: biopython>=1.81
Requires-Dist: packaging>=23.2
Dynamic: author
Dynamic: author-email
Dynamic: classifier
Dynamic: description
Dynamic: download-url
Dynamic: home-page
Dynamic: keywords
Dynamic: license
Dynamic: license-file
Dynamic: requires-dist
Dynamic: summary
